hide_env.py
hide_env-1.0.0.data/purelib/hide_env-1.0.0-py3.5.egg-info/dependency_links.txt
hide_env-1.0.0.data/purelib/hide_env-1.0.0-py3.5.egg-info/entry_points.txt
hide_env-1.0.0.data/purelib/hide_env-1.0.0-py3.5.egg-info/PKG-INFO
hide_env-1.0.0.data/purelib/hide_env-1.0.0-py3.5.egg-info/requires.txt
hide_env-1.0.0.data/purelib/hide_env-1.0.0-py3.5.egg-info/SOURCES.txt
hide_env-1.0.0.data/purelib/hide_env-1.0.0-py3.5.egg-info/top_level.txt
hide_env-1.0.0.dist-info/DESCRIPTION.rst
hide_env-1.0.0.dist-info/entry_points.txt
hide_env-1.0.0.dist-info/METADATA
hide_env-1.0.0.dist-info/metadata.json
hide_env-1.0.0.dist-info/RECORD
hide_env-1.0.0.dist-info/top_level.txt
hide_env-1.0.0.dist-info/WHEEL
