Metadata-Version: 2.0
Name: hide-env
Version: 1.0.0
Summary: Hide environment variables from output.
Home-page: http://github.com/relekang/hide-env
Author: Rolf Erik Lekang
Author-email: me@rolflekang.com
License: MIT
Platform: UNKNOWN
Classifier: Programming Language :: Python
Classifier: Programming Language :: Python :: 2
Classifier: Programming Language :: Python :: 2.7
Classifier: Programming Language :: Python :: 3
Classifier: Programming Language :: Python :: 3.4
Requires-Dist: click (==6.2)
